.DS_Store
.gitignore
LICENSE.txt
README.md
setup.py
draw2Svg/__init__.py
draw2Svg/animation.py
draw2Svg/color.py
draw2Svg/defs.py
draw2Svg/drawing.py
draw2Svg/elements.py
draw2Svg/missing.py
draw2Svg/raster.py
draw2Svg/video.py
draw2Svg.egg-info/PKG-INFO
draw2Svg.egg-info/SOURCES.txt
draw2Svg.egg-info/dependency_links.txt
draw2Svg.egg-info/requires.txt
draw2Svg.egg-info/top_level.txt
draw2Svg/widgets/__init__.py
draw2Svg/widgets/async_animation.py
draw2Svg/widgets/drawing_javascript.py
draw2Svg/widgets/drawing_widget.py
examples/.DS_Store
examples/animated-fix-github.svg
examples/animated.svg
examples/example1.png
examples/example1.svg
examples/example2.png
examples/example2.svg
examples/example3.png
examples/example3.svg
examples/example4.png
examples/example4.svg
examples/example5.gif
examples/example6.gif
examples/example7.gif