Metadata-Version: 2.1
Name: draw2Svg
Version: 2.0.0
Summary: A Python 3 library for programmatically generating SVG images (vector drawings) and rendering them or displaying them in a Jupyter notebook
Home-page: https://github.com/cduck/drawSvg
Download-URL: https://github.com/aufarah/New-drawSvg/archive/2.0.0.tar.gz
Author: Casey Duckering, Ahmad Aufar
License: UNKNOWN
Keywords: SVG,draw,graphics,iPython,Jupyter,widget
Platform: UNKNOWN
Classifier: License :: OSI Approved :: MIT License
Classifier: Programming Language :: Python :: 3
Classifier: Framework :: IPython
Classifier: Framework :: Jupyter
License-File: LICENSE.txt
